{
"type": "FeatureCollection",
"name": "Contaminacion_auditiva_2026_V4",
"crs": { "type": "name", "properties": { "name": "urn:ogc:def:crs:OGC:1.3:CRS84" } },
"features": [
{ "type": "Feature", "properties": { "Name": "Contaminación auditiva", "descriptio": null, "timestamp": null, "begin": null, "end": null, "altitudeMo": null, "tessellate": -1, "extrude": 0, "visibility": -1, "drawOrder": null, "icon": null, "nom_marca": "Contaminación auditiva", "sitio": "Contaminación auditiva", "LOCALIDAD": "San Pedro Barrientos", "MUNICIPIO": "Tlalnepantla", "ESTADO": "Estado de México", "conflicto": "Corredor urbano-industrial entre Tlalnepantla, Tultitlán, Cuautitlán y Tepotzotlán", "Saber mas": "https:\/\/organizacion.renacerambiental.org\/es\/node\/300\/", "descrip": "El manto de contaminación atmosférica tradicional de la megaciudad de México cobija la megaindustrialización y megaurbanización salvajes de esta región, con concentración de empresas altamente contaminantes de los sectores químico, metalúrgico," }, "geometry": { "type": "Point", "coordinates": [ -99.200936948001598, 19.5755240796938, 0.0 ] } },
{ "type": "Feature", "properties": { "Name": "Contaminación auditiva", "descriptio": null, "timestamp": null, "begin": null, "end": null, "altitudeMo": null, "tessellate": -1, "extrude": 0, "visibility": -1, "drawOrder": null, "icon": null, "nom_marca": "Contaminación auditiva", "sitio": "Contaminación auditiva", "LOCALIDAD": "San Pedro Barrientos", "MUNICIPIO": "Tlalnepantla", "ESTADO": "Estado de México", "conflicto": "Corredor urbano-industrial entre Tlalnepantla, Tultitlán, Cuautitlán y Tepotzotlán", "Saber mas": "https:\/\/organizacion.renacerambiental.org\/es\/node\/300\/", "descrip": "El manto de contaminación atmosférica tradicional de la megaciudad de México cobija la megaindustrialización y megaurbanización salvajes de esta región, con concentración de empresas altamente contaminantes de los sectores químico, metalúrgico," }, "geometry": { "type": "Point", "coordinates": [ -99.202018947122482, 19.584611461660739, 0.0 ] } }
]
}
